aiofunctools/__init__.py
aiofunctools-0.0.3.dist-info/LICENSE
aiofunctools-0.0.3.dist-info/METADATA
aiofunctools-0.0.3.dist-info/WHEEL
aiofunctools-0.0.3.dist-info/top_level.txt
aiofunctools-0.0.3.dist-info/RECORD
