Metadata-Version: 2.1
Name: aiofunctools
Version: 0.0.3
Summary: Python functools for async!
Home-page: http://github.com/pando85/aiofunctools
Author: Pando85
Author-email: pand855@gmail.com
License: GPLv3+
Keywords: aiofunctools functools
Platform: UNKNOWN
Classifier: Development Status :: 3 - Alpha
Classifier: License :: OSI Approved :: GNU General Public License (GPL)
Classifier: Programming Language :: Python :: 3.7
Classifier: Topic :: Internet :: WWW/HTTP :: HTTP Servers
Classifier: Intended Audience :: Developers
Requires-Dist: toolz (>=0.9.0)
